{"type":"FeatureCollection","crs":{"type":"name","properties":{"name":"EPSG:4269"}},"features":[{"type":"Feature","id":1,"geometry":{"type":"Point","coordinates":[-83.361229444999935,35.463251440000079]},"properties":{"OBJECTID":1,"Label":"Zone 1"}},{"type":"Feature","id":2,"geometry":{"type":"Point","coordinates":[-83.335728383999935,35.478091870000071]},"properties":{"OBJECTID":2,"Label":"Zone 2"}},{"type":"Feature","id":3,"geometry":{"type":"Point","coordinates":[-83.315002814999957,35.465626389000079]},"properties":{"OBJECTID":3,"Label":"Zone 3"}},{"type":"Feature","id":4,"geometry":{"type":"Point","coordinates":[-83.286007330999951,35.47351468800008]},"properties":{"OBJECTID":4,"Label":"Zone 4"}},{"type":"Feature","id":5,"geometry":{"type":"Point","coordinates":[-83.258149111999955,35.47378109400006]},"properties":{"OBJECTID":5,"Label":"Zone 5"}},{"type":"Feature","id":6,"geometry":{"type":"Point","coordinates":[-83.23141127699995,35.473953225000059]},"properties":{"OBJECTID":6,"Label":"Zone 6"}},{"type":"Feature","id":7,"geometry":{"type":"Point","coordinates":[-83.286482350999961,35.519372136000072]},"properties":{"OBJECTID":7,"Label":"Zone 7"}},{"type":"Feature","id":8,"geometry":{"type":"Point","coordinates":[-83.27867140099994,35.531001411000034]},"properties":{"OBJECTID":8,"Label":"Zone 8"}},{"type":"Feature","id":9,"geometry":{"type":"Point","coordinates":[-83.27110801799995,35.545326949000071]},"properties":{"OBJECTID":9,"Label":"Zone 9"}},{"type":"Feature","id":10,"geometry":{"type":"Point","coordinates":[-83.253083087999983,35.558369291000076]},"properties":{"OBJECTID":10,"Label":"Zone 10"}},{"type":"Feature","id":11,"geometry":{"type":"Point","coordinates":[-83.233671480999988,35.55563386700004]},"properties":{"OBJECTID":11,"Label":"Zone 11"}},{"type":"Feature","id":12,"geometry":{"type":"Point","coordinates":[-83.217440156999942,35.543552925000029]},"properties":{"OBJECTID":12,"Label":"Zone 12"}}]}